<metadata xml:lang="en"><Esri><CreaDate>2020-09-02T10:02:04</CreaDate><CreaTime>00000000</CreaTime><ArcGISFormat>1.0</ArcGISFormat><ArcGISstyle>North American Profile of ISO19115 2003</ArcGISstyle><SyncOnce>FALSE</SyncOnce><DataProperties><itemProps><itemName Sync="TRUE">Guatemala_adm1_uscb_2020</itemName><nativeExtBox><westBL Sync="TRUE">-92.231135</westBL><eastBL Sync="TRUE">-88.231693</eastBL><southBL Sync="TRUE">13.740021</southBL><northBL Sync="TRUE">17.815695</northBL><exTypeCode Sync="TRUE">1</exTypeCode></nativeExtBox><itemSize Sync="TRUE">0.844</itemSize><itemLocation Sync="FALSE"><linkage Sync="FALSE"/><protocol Sync="FALSE"/></itemLocation><imsContentType Sync="TRUE">002</imsContentType></itemProps><coordRef><type Sync="TRUE">Geographic</type><geogcsn Sync="TRUE">GCS_WGS_1984</geogcsn><csUnits Sync="TRUE">Angular Unit: Degree (0.017453)</csUnits><peXml Sync="TRUE">&lt;GeographicCoordinateSystem xsi:type='typens:GeographicCoordinateSystem' xmlns:xsi='http://www.w3.org/2001/XMLSchema-instance' xmlns:xs='http://www.w3.org/2001/XMLSchema' xmlns:typens='http://www.esri.com/schemas/ArcGIS/10.5'&gt;&lt;WKT&gt;GEOGCS[&amp;quot;GCS_WGS_1984&amp;quot;,DATUM[&amp;quot;D_WGS_1984&amp;quot;,SPHEROID[&amp;quot;WGS_1984&amp;quot;,6378137.0,298.257223563]],PRIMEM[&amp;quot;Greenwich&amp;quot;,0.0],UNIT[&amp;quot;Degree&amp;quot;,0.0174532925199433],AUTHORITY[&amp;quot;EPSG&amp;quot;,4326]]&lt;/WKT&gt;&lt;XOrigin&gt;-400&lt;/XOrigin&gt;&lt;YOrigin&gt;-400&lt;/YOrigin&gt;&lt;XYScale&gt;11258999068426.238&lt;/XYScale&gt;&lt;ZOrigin&gt;-100000&lt;/ZOrigin&gt;&lt;ZScale&gt;10000&lt;/ZScale&gt;&lt;MOrigin&gt;-100000&lt;/MOrigin&gt;&lt;MScale&gt;10000&lt;/MScale&gt;&lt;XYTolerance&gt;8.983152841195215e-009&lt;/XYTolerance&gt;&lt;ZTolerance&gt;0.001&lt;/ZTolerance&gt;&lt;MTolerance&gt;0.001&lt;/MTolerance&gt;&lt;HighPrecision&gt;true&lt;/HighPrecision&gt;&lt;LeftLongitude&gt;-180&lt;/LeftLongitude&gt;&lt;WKID&gt;4326&lt;/WKID&gt;&lt;LatestWKID&gt;4326&lt;/LatestWKID&gt;&lt;/GeographicCoordinateSystem&gt;</peXml></coordRef><copyHistory Sync="FALSE"/></DataProperties><SyncDate>20201203</SyncDate><SyncTime>08335000</SyncTime><ModDate>20201203</ModDate><ModTime>08335000</ModTime><scaleRange><minScale>150000000</minScale><maxScale>5000</maxScale></scaleRange><ArcGISProfile>ISO19139</ArcGISProfile></Esri><eainfo><detailed Name="Guatemala_adm1_uscb_2020" xmlns=""><enttyp><enttypl Sync="TRUE">Guatemala_adm1_uscb_2020</enttypl><enttypt Sync="TRUE">Feature Class</enttypt><enttypc Sync="TRUE">22</enttypc></enttyp><attr xmlns=""><attrlabl Sync="TRUE">FID</attrlabl><attalias Sync="TRUE">FID</attalias><attrtype Sync="TRUE">OID</attrtype><attwidth Sync="TRUE">4</attwidth><atprecis Sync="TRUE">0</atprecis><attscale Sync="TRUE">0</attscale><attrdef Sync="TRUE">Internal feature number.</attrdef><attrdefs Sync="TRUE">Esri</attrdefs><attrdomv><udom Sync="TRUE">Sequential unique whole numbers that are automatically generated.</udom></attrdomv></attr><attr xmlns=""><attrlabl Sync="TRUE">Shape</attrlabl><attalias Sync="TRUE">Shape</attalias><attrtype Sync="TRUE">Geometry</attrtype><attwidth Sync="TRUE">0</attwidth><atprecis Sync="TRUE">0</atprecis><attscale Sync="TRUE">0</attscale><attrdef Sync="TRUE">Feature geometry.</attrdef><attrdefs Sync="TRUE">Esri</attrdefs><attrdomv><udom Sync="TRUE">Coordinates defining the features.</udom></attrdomv></attr><attr xmlns=""><attrlabl Sync="TRUE">Shape_Leng</attrlabl><attalias Sync="FALSE">Shape_Length</attalias><attrtype Sync="TRUE">Double</attrtype><attwidth Sync="TRUE">19</attwidth><atprecis Sync="TRUE">0</atprecis><attscale Sync="TRUE">0</attscale><attrdef>Length of feature in internal units.</attrdef><attrdefs>Esri</attrdefs><attrdomv><udom>Positive real numbers that are automatically generated.</udom></attrdomv></attr><attr xmlns=""><attrlabl Sync="TRUE">Shape_Area</attrlabl><attalias Sync="TRUE">Shape_Area</attalias><attrtype Sync="TRUE">Double</attrtype><attwidth Sync="TRUE">19</attwidth><atprecis Sync="TRUE">0</atprecis><attscale Sync="TRUE">0</attscale><attrdef Sync="TRUE">Area of feature in internal units squared.</attrdef><attrdefs Sync="TRUE">Esri</attrdefs><attrdomv><udom Sync="TRUE">Positive real numbers that are automatically generated.</udom></attrdomv></attr><attr xmlns=""><attrlabl>AREA_NAME</attrlabl><attrdef>Name of the country or subnational area (administrative division).</attrdef><attrdefs>U.S. Board on Geographic Names, 2020</attrdefs><attalias Sync="TRUE">AREA_NAME</attalias><attrtype Sync="TRUE">String</attrtype><attwidth Sync="TRUE">254</attwidth><atprecis Sync="TRUE">0</atprecis><attscale Sync="TRUE">0</attscale></attr><attr xmlns=""><attrlabl>GEO_CONCAT</attrlabl><attrdef>Concatenation of all administrative division names separated by underscores ("_"), beginning with the country name and ending with the division name for the lowest subnational administrative order (level). The field serves as one for name sorting and ordering.</attrdef><attrdefs>Population Division, U.S. Census Bureau</attrdefs><attalias Sync="TRUE">GEO_CONCAT</attalias><attrtype Sync="TRUE">String</attrtype><attwidth Sync="TRUE">254</attwidth><atprecis Sync="TRUE">0</atprecis><attscale Sync="TRUE">0</attscale></attr><attr xmlns=""><attrlabl>GEO_MATCH</attrlabl><attrdef>Identical subnational area identifiers in the Excel table, geospatial data file, and Unicode text table, enabling linkage (joining) of the table records to the geospatial data file polygons as attributes.</attrdef><attrdefs>Population Division, U.S. Census Bureau</attrdefs><attalias Sync="TRUE">GEO_MATCH</attalias><attrtype Sync="TRUE">String</attrtype><attwidth Sync="TRUE">254</attwidth><atprecis Sync="TRUE">0</atprecis><attscale Sync="TRUE">0</attscale></attr><attr xmlns=""><attrlabl>CNTRY_NAME</attrlabl><attrdef>Country name.</attrdef><attrdefs>U.S. Board on Geographic Names, 2020</attrdefs><attalias Sync="TRUE">CNTRY_NAME</attalias><attrtype Sync="TRUE">String</attrtype><attwidth Sync="TRUE">100</attwidth><atprecis Sync="TRUE">0</atprecis><attscale Sync="TRUE">0</attscale></attr><attr xmlns=""><attrlabl>ADM1_NAME</attrlabl><attrdef>First-order administrative division name (ADM1), i.e., departamentos.</attrdef><attrdefs>U.S. Board on Geographic Names, 2020</attrdefs><attalias Sync="TRUE">ADM1_NAME</attalias><attrtype Sync="TRUE">String</attrtype><attwidth Sync="TRUE">100</attwidth><atprecis Sync="TRUE">0</atprecis><attscale Sync="TRUE">0</attscale></attr><attr xmlns=""><attrlabl>ADM_LEVEL</attrlabl><attrdef>Administrative level "0" (ADM0/country); administrative level  "1"  (ADM1); administrative level "2" (ADM2); administrative level "3" (ADM3); administrative level "4" (ADM4).</attrdef><attrdefs>Population Division, U.S. Census Bureau</attrdefs><attalias Sync="TRUE">ADM_LEVEL</attalias><attrtype Sync="TRUE">String</attrtype><attwidth Sync="TRUE">15</attwidth><atprecis Sync="TRUE">0</atprecis><attscale Sync="TRUE">0</attscale></attr><attr xmlns=""><attrlabl>GENC_CODE</attrlabl><attrdef>U.S. Government Geopolitical Entities, Names, and Codes (GENC) Standard (for country and first-order administrative divisions only).</attrdef><attrdefs>U.S. Government Geopolitical Entities, Names, and Codes (GENC), 2020</attrdefs><attalias Sync="TRUE">GENC_CODE</attalias><attrtype Sync="TRUE">String</attrtype><attwidth Sync="TRUE">10</attwidth><atprecis Sync="TRUE">0</atprecis><attscale Sync="TRUE">0</attscale></attr><attr xmlns=""><attrlabl>FIPS_CODE</attrlabl><attrdef>U.S. Government Federal Information Processing System (FIPS) code (for country and first-order administrative divisions only).</attrdef><attrdefs>U.S. Government Federal Information Processing System (FIPS), 2020</attrdefs><attalias Sync="TRUE">FIPS_CODE</attalias><attrtype Sync="TRUE">String</attrtype><attwidth Sync="TRUE">10</attwidth><atprecis Sync="TRUE">0</atprecis><attscale Sync="TRUE">0</attscale></attr><attr xmlns=""><attrlabl>NSO_CODE</attrlabl><attrdef>Code used by the Instituto Nacional de Estadística Guatemala for a subnational administrative division.</attrdef><attrdefs>Instituto Nacional de Estadística Guatemala, 2018</attrdefs><attalias Sync="TRUE">NSO_CODE</attalias><attrtype Sync="TRUE">String</attrtype><attwidth Sync="TRUE">20</attwidth><atprecis Sync="TRUE">0</atprecis><attscale Sync="TRUE">0</attscale></attr></detailed></eainfo><mdLang><languageCode value="eng"/><countryCode Sync="TRUE" value="USA"/></mdLang><mdChar><CharSetCd value="004"/></mdChar><mdHrLv><ScopeCd value="005"/></mdHrLv><mdDateSt Sync="TRUE">20201203</mdDateSt><mdStanName>ArcGIS Metadata</mdStanName><mdStanVer>1.0</mdStanVer><distInfo><distFormat><formatName Sync="TRUE">Shapefile</formatName><formatVer>1</formatVer></distFormat><distTranOps><transSize Sync="TRUE">0.844</transSize></distTranOps></distInfo><dataIdInfo><idCitation><resTitle Sync="FALSE">Guatemala: First-Order Administrative Divisions</resTitle><date><createDate>2020-09-02T10:02:04</createDate></date><citRespParty><rpIndName>Population Division</rpIndName><rpOrgName>U.S. Census Bureau</rpOrgName><rpCntInfo><cntPhone><voiceNum tddtty="">301-763-2419</voiceNum></cntPhone><cntAddress addressType="postal"><delPoint>4600 Silver Hill Rd</delPoint><city>Washington</city><adminArea>DC</adminArea><postCode>20233-8800</postCode><eMailAdd>pop.global.map.list@census.gov</eMailAdd><country>US</country></cntAddress></rpCntInfo><role><RoleCd value="011">11</RoleCd></role></citRespParty><presForm><PresFormCd value="005"/></presForm></idCitation><idAbs>&lt;DIV STYLE="text-align:Left;"&gt;&lt;DIV&gt;&lt;DIV&gt;&lt;P&gt;&lt;SPAN&gt;Annual Five-Year Age Group Population Estimates by Sex for 2000 to 2025 for the national and first-order administrative division levels of Guatemala were prepared by the U.S. Census Bureau for joining (linking) to shapefiles as attribute data. The estimates are consistent with the midyear national projections from the U.S. Census Bureau International Data Base (IDB).&lt;/SPAN&gt;&lt;/P&gt;&lt;/DIV&gt;&lt;/DIV&gt;&lt;/DIV&gt;</idAbs><idPurp>The U.S. Census Bureau is providing annual subnational five-year age group population estimates by sex for Guatemala for 2000-2025 in a geographic information system (GIS) for users of the Spatial Data Repository, funded by the U.S. President’s Emergency Plan for AIDS Relief (PEPFAR).</idPurp><idCredit>CENSUS DATA
2018 Age-Sex Data: XII Censo Nacional de Población y VII de Vivienda, 2018, Población por Edad y Sexo. Instituto Nacional de Estadística Guatemala. Available online at http://redatam.censopoblacion.gt/bingtm/RpWebEngine.exe/Portal?BASE=CPVGT2018&amp;lang=esp (Indicadores Generales, Personas, Pirámide de población, Nivel de resultado: Municipal, Salida: Tabla, accessed September 02, 2020).

2002 Population Total Data: Censos Nacionales XI de Población y VI de Habitación, 2002, Características de la Población y de los Locales de Habitación Censados, Cuadro A1 - Población Total, Sexo, Grupos de Edad y Área Urbana y Rural, Según Departamento y Municipio. Instituto Nacional de Estadística Guatemala. Available online at http://www.ine.gob.gt/sistema/uploads/2014/02/20/jZqeGe1H9WdUDngYXkWt3GIhUUQCukcg.pdf (accessed September 02, 2020).

The U.S. Census Bureau cannot guarantee the accuracy of non-U.S. census and survey data.

GEOSPATIAL BOUNDARIES
International boundaries coincide with the Large Scale International Boundaries (LSIB) dataset from the U.S. Department of State, Office of the Geographer and Global Issues. Available online at http://geonode.state.gov (accessed September 01, 2020). Geospatial data for the first-order administrative divisions of Guatemala were downloaded from the Humanitarian Data Exchange, available online at http://data.humdata.org/dataset/guatemala-administrative-level-0-national-1-departments-and-2-municipalities, "gtm_admbnda_adm2_ocha_conred_20190207" (accessed September 01, 2020).

The U.S. Census Bureau cannot guarantee the accuracy of boundary placements.

NATIONAL ESTIMATES AND PROJECTIONS
U.S. Census Bureau, Population Division. International Data Base, December 2019 release, available online at http://www.census.gov/data-tools/demo/idb/informationGateway.php, accessed September 01, 2020.

NATIONAL AND SUBNATIONAL AREA NAMES AND CODES
(1) U.S. National Geospatial-Intelligence Agency. NGA GEOnet Names Server (GNS), available at http://geonames.nga.mil/gns/html/ (accessed September 01, 2020). Contains geographic area names from the U.S. Board on Geographic Names and the U.S. Government Federal Information Processing System (FIPS) codes.
(2) U.S. Government Geopolitical Entities, Names, and Codes (GENC) Standard. NSG Standards Registry, available at http://nsgreg.nga.mil/genc/discovery (accessed September 01, 2020).</idCredit><placeKeys><keyword>Guatemala, Departamento</keyword></placeKeys><tempKeys><keyword>2020</keyword></tempKeys><themeKeys><keyword>Subnational Divisions</keyword></themeKeys><searchKeys><keyword>Geospatial Boundaries</keyword><keyword>Guatemala</keyword><keyword>First-Order Administrative Divisions</keyword><keyword>Departamento</keyword></searchKeys><resConst><Consts><useLimit>&lt;DIV STYLE="text-align:Left;"&gt;&lt;DIV&gt;&lt;DIV&gt;&lt;P&gt;&lt;SPAN&gt;U.S. Census Bureau population estimates: None. Acknowledgment of the Census Bureau would be appreciated in products derived from its population estimates. The subnational boundaries used for this shapefile were downloaded by the U.S. Census Bureau from a publicly available source for this product. The international boundaries are derived from the Large Scale International Boundaries (LSIB) dataset (public domain).&lt;/SPAN&gt;&lt;/P&gt;&lt;/DIV&gt;&lt;/DIV&gt;&lt;/DIV&gt;</useLimit></Consts></resConst><spatRpType><SpatRepTypCd value="001"/></spatRpType><dataLang><languageCode value="eng"/><countryCode Sync="TRUE" value="USA"/></dataLang><dataChar><CharSetCd value="004"/></dataChar><envirDesc Sync="FALSE"/><suppInfo>SUBNATIONAL DIVISIONS
Guatemala's first-order administrative divisions: 22 departamentos as of the 2018 census.

SHAPEFILES
The original shapefile downloaded from the Humanitarian Data Exchange had 342 polygons, one for each of Guatemala's 340 second-order administrative divisions (municipios) as reported by the Instituto Nacional de Estadística Guatemala, one for Lago de Amatitlán, and one for Lago de Atitlán. The polygons representing the two lakes were classified as second-order administrative divisions in the original shapefile as part of Guatemala and Sololá departamentos, respectively. No changes were made to the subnational boundaries by USCB staff. The U.S. Census Bureau aligned the shapefile's national boundary to the Large Scale International Boundary Line (LSIB) polygon file from the U.S. Department of State, Office of the Geographer and Global Issues. Finally, the LSIB-aligned shapefile was dissolved into 22 polygons, one for each of Guatemala's first-order administrative divisions (departamentos) as reported by the Instituto Nacional de Estadística Guatemala in the 2018 census.

CENSUS DATA INTERPOLATION
The 2002 census totals had the following differences in geography that have been modified to their 2018 locations in the estimates presented here, requiring interpolation and adjustment of 2002 population data by USCB staff:
(1) There were a total of 9 new municipios that were formed between Guatemala's 2002 and 2018 censuses, as noted in the USCBCMNT field.

New municipios were each fully formed from part of a single area, and boundaries and population data were not available for the next administrative level down. The total population of the original area in 2002 was divided proportionally according to the populations of the new areas in 2018. 

ADDITIONAL NOTES
(1) Características de la Población y de los Locales de Habitación Censados was published by the Instituto Nacional de Estadística Guatemala as a scanned PDF document that was not machine-readable. 2002 population totals from this publication were manually transcribed by USCB staff.
(2) The USCBCMNT field includes alternate names for some second-order administrative divisions.

FEATURE AND ATTRIBUTE DETAILS
The 2000-2025 population estimates for Guatemala's administrative divisions are provided in the following two tables:
(1) The Unicode tab-delimited text file (table) "Guatemala_5yr_age_sex_2000-2025_uscb_nov2020.txt," which can be joined to the shapefile via the common field "GEOMATCH."
(2) The Excel table "Guatemala_5yr_age_sex_2000-2025_508_uscb_nov2020.xlsx," formatted for accessibility in compliance with Section 508 of the U.S. Government's Federal Rehabilitation Act.

Details on processing of the census data and calculation of 2000-2025 estimates are provided in the "Census Metadata" tab of the Excel file and "Methods for Calculating 5-Year Age Group Population Estimates by Sex for Subnational Areas" document. For the subnational areas, the U.S. Board on Geographic Names (BGN) "approved" names from the NGA GEOnet Names Server (cited in the "Credits") were used. For any area that a BGN name was not available, the name from the national census was used. Official codes for the subnational areas from the country's national statistical office, when available, are entered in the "NSO_CODE" field in both the text and Excel tables. Information on any alternative area names or recent name or boundary changes is entered in the "USCBCMNT" field. A partial list of the fields in the Excel and Unicode text files, including all fields identifying geographic names and codes, is provided in the Excel file's "Data Dictionary" tab. More detail on the U.S. Census Bureau subnational age and sex group estimates and maps for PEPFAR can be found in the document "Subnational Population Estimates Components for the Spatial Data Repository." It includes a data dictionary that is similar to that in the Excel table.

METHODOLOGY
For more information, see the following methodology documents in the Spatial Data Repository:
(1) "U.S. Census Bureau Methodology for SDR Subnational Population Estimates."
(2) "U.S. Census Bureau Methods for Calculating 5-Year Age Group Population Estimates by Sex for Subnational Areas."
(3) "Instructions for Joining Subnational Population Data to Shapefiles."

ACCESS
The U.S. Census Bureau’s products for PEPFAR can be accessed from the Spatial Data Repository at http://spatialdata.dhsprogram.com/home/, which also provides access to data and maps from the DHS (Demographic and Health Surveys) Program. A zipped file containing shapefiles with metadata, an Excel workbook with subnational population estimates, and a Unicode tab-delimited text file is available for each country. PEPFAR products are also available on the Census Bureau website at http://www.census.gov/geographies/mapping-files/time-series/demo/international-programs/subnationalpopulation.html for download.</suppInfo><idPoC><rpIndName>Population Division</rpIndName><rpOrgName>U.S. Census Bureau</rpOrgName><rpCntInfo><cntPhone><voiceNum tddtty="">301-763-2419</voiceNum></cntPhone><cntAddress addressType="postal"><delPoint>4600 Silver Hill Rd</delPoint><city>Washington</city><adminArea>DC</adminArea><postCode>20233-8800</postCode><eMailAdd>pop.global.map.list@census.gov</eMailAdd><country>US</country></cntAddress></rpCntInfo><role><RoleCd value="011">11</RoleCd></role><displayName>U.S. Census Bureau</displayName></idPoC><dataExt><geoEle xmlns=""><GeoBndBox esriExtentType="search"><exTypeCode Sync="TRUE">1</exTypeCode><westBL Sync="TRUE">-92.231135</westBL><eastBL Sync="TRUE">-88.231693</eastBL><northBL Sync="TRUE">17.815695</northBL><southBL Sync="TRUE">13.740021</southBL></GeoBndBox></geoEle></dataExt><tpCat><TopicCatCd value="016"/></tpCat><tpCat><TopicCatCd value="013"/></tpCat></dataIdInfo><mdMaint><maintFreq><MaintFreqCd value="009">9</MaintFreqCd></maintFreq></mdMaint><spatRepInfo><VectSpatRep><geometObjs Name="Guatemala_adm1_uscb_2020"><geoObjTyp><GeoObjTypCd value="002" Sync="TRUE"></GeoObjTypCd></geoObjTyp><geoObjCnt Sync="TRUE">22</geoObjCnt></geometObjs><topLvl><TopoLevCd value="001" Sync="TRUE"></TopoLevCd></topLvl></VectSpatRep></spatRepInfo><refSysInfo><RefSystem dimension="horizontal"><refSysID><identCode code="4326"/><idCodeSpace Sync="TRUE">EPSG</idCodeSpace><idVersion Sync="TRUE">6.14(3.0.1)</idVersion></refSysID></RefSystem></refSysInfo><mdHrLvName Sync="TRUE">dataset</mdHrLvName><spdoinfo><ptvctinf><esriterm Name="Guatemala_adm1_uscb_2020"><efeatyp Sync="TRUE">Simple</efeatyp><efeageom code="4" Sync="TRUE"></efeageom><esritopo Sync="TRUE">FALSE</esritopo><efeacnt Sync="TRUE">22</efeacnt><spindex Sync="TRUE">FALSE</spindex><linrefer Sync="TRUE">FALSE</linrefer></esriterm></ptvctinf></spdoinfo><Binary><Thumbnail><Data EsriPropertyType="PictureX">/9j/4AAQSkZJRgABAQEAAQABAAD/2wBDAAgGBgcGBQgHBwcJCQgKDBQNDAsLDBkSEw8UHRofHh0a
HBwgJC4nICIsIxwcKDcpLDAxNDQ0Hyc5PTgyPC4zNDL/2wBDAQkJCQwLDBgNDRgyIRwhMjIyMjIy
MjIyMjIyMjIyMjIyMjIyMjIyMjIyMjIyMjIyMjIyMjIyMjIyMjIyMjIyMjL/wAARCACFAMgDASIA
AhEBAxEB/8QAHwAAAQUBAQEBAQEAAAAAAAAAAAECAwQFBgcICQoL/8QAtRAAAgEDAwIEAwUFBAQA
AAF9AQIDAAQRBRIhMUEGE1FhByJxFDKBkaEII0KxwRVS0fAkM2JyggkKFhcYGRolJicoKSo0NTY3
ODk6Q0RFRkdISUpTVFVWV1hZWmNkZWZnaGlqc3R1dnd4eXqDhIWGh4iJipKTlJWWl5iZmqKjpKWm
p6ipqrKztLW2t7i5usLDxMXGx8jJytLT1NXW19jZ2uHi4+Tl5ufo6erx8vP09fb3+Pn6/8QAHwEA
AwEBAQEBAQEBAQAAAAAAAAECAwQFBgcICQoL/8QAtREAAgECBAQDBAcFBAQAAQJ3AAECAxEEBSEx
BhJBUQdhcRMiMoEIFEKRobHBCSMzUvAVYnLRChYkNOEl8RcYGRomJygpKjU2Nzg5OkNERUZHSElK
U1RVVldYWVpjZGVmZ2hpanN0dXZ3eHl6goOEhYaHiImKkpOUlZaXmJmaoqOkpaanqKmqsrO0tba3
uLm6wsPExcbHyMnK0tPU1dbX2Nna4uPk5ebn6Onq8vP09fb3+Pn6/9oADAMBAAIRAxEAPwD3+iii
gAooooAKKKKACiiigApkkqRKC5PJwMAn+VPqC56w/wC//wCymoqS5YOS6Ag+1xf9NP8Av03+FH2u
L/pp/wB+m/wptFeb9fqdkaciHfa4v+mn/fpv8KPtcX/TT/v03+FNoo+v1OyDkQ77XF/00/79N/hR
9ri/6af9+m/wptFH1+p2QciJI7iOV9q7t2M4ZCP5ipaqx/8AH2n+4381q1XoUKjqU1JkNWYUUUVq
IKKKKACiiigAooooAKKKKACiiigAooooAKKKKAIFvIXUMpcqRkERtgj8qjmmSR4Qofh8nKMAPlPt
STWYVjNbrtl3bmUEgPwRgjpnnr7CiORZASpPBwQRgg+4rhxVWpBOLWj6lRSY+iiivJNAooooAKKK
KAEj/wCPtP8Acb+a1aqrH/x9p/uN/NatV7eE/gr+upnLcKKKK6SQooooAKKKKACiiigAooooAKKK
KACiiigAooooAKqXVitwfMSWSGYYw6N1xnAI6Ec1bopNJqzAol5IWVZwMMcCRfuk54BHY/p71LUl
zEZ7aWIHBdCoPocdapQ3WEjS6VoJivIk6E8ZwRwea8rFYbk96C0NIyvuWaKKK4SgooooAIObqTPZ
Fx7ZJz/IflVmq0H/AB8y/wC4v82qzXu4VWoxMpbhRRRW4gooooAKKKKACiiigAooooAKKKKACiii
gAoqG4cgCNThnzyOw7n/AD61D5Y/vy/9/G/xrnq4qFJ8rGotlyiqflj+/L/38b/GoYg/myxyNJlc
MpErYKknHfrx/npWX16n2f8AXzHyM0qoasPMtFtzgJcSCJzuIO05zgjvxj8ajuN4eOGJ3DyHO5pW
+VRjPfk88f5zC1ndzOiyzqEjkDh1LEnB6YJIH60pY2Di7XQcrNCiovLkHInYn/bUEfpiojLdRSZk
hV4j1MRJZfwPX8PyNeXY0LVFVjLcTHFugRQcGSZT+i8E/iR+NLHN5cK+c5Zi7ICF5JBPYewosBZt
uXnJ6hwv4bQf6mrFZ8N9bxmXc7Al/u7Gz0A6Y9v5etW47mCb/VzIx4yAwyOv+B/KvcoWVOK8jJ7k
tFQXF2ls8YkVwjnHmY+Vfqe1TAhgCCCDyCK2uIWiiigAooooAKKKKACiiigAooooAKQkKCSQAOST
2paqXMoMyQYO0n5iOmcZA/r/APrqKk1Ti5MaVwUl2aVgQW6A9h2H+fWnVG1xArlGmjDDqCwqQEEZ
ByDXgzk5Scn1NURTTpAoLn5mOFUdWPoBSW0PkwqGLGQgFyzFjn6mhxsnErKWG3AIGdv4e/8ASpEd
ZEV15VgCOMcUugFZy0d40sqloQg8sqpO087untjmrSsGUMpBBGQR3qG7mMEBcBOuMucKPcnB4otW
iEQiilSTywAdpHH+FD1VwJ6KKKkAqrbwRtcPdiNAzcKwXB28cn6kflip5UaSF0VtjMpAbGcH1qm8
tx9kikjVURWxIIzztzjK8Ee9XBXdk9wZeZlRSzMFUDJJOAKzGWbVSCMw2hBw+1SzgjtnO3n2zx+V
tBGFVksWaXqJZgoOc5yecj8vyqaKMRRKgPT0GB+A7CtpwjSWkrv8hJ3K7W7yusEwWa0Ubh5vzNnk
YOeowep5+vZ7F4JVFrEzuxy0YIC4zyTk8fhz7GpN7SyeXCM4Pzuei+3ufb8+2bUcSxLhc5PJJ6k+
9dOHhVqSVST0X4ktpaD6KKK9IgKKKKACiiigAooooAKKKKACqU0KiUB8kOxZWDEHdjpx7Z/D6Vdq
g6+bqMjksViVVUE8BuSTj1wRz/8AXrmxfL7J3KjuSIixoERQqjoAKppK6sjwqxhdiBGcZJ9vToTz
9OKtTSeVEXxk5AA9STgfqai8mVY4ipUukhdl6Bs5zz2+9n8K8ZGhBcBjKrXCzGKQ+WI0Ygr7nb1z
g/StCqUk7zxI0UcgcHIJXgMOqn9RmlF207iOAoHXd5ivzgggY4PHXr7dPRtNoCRl33mJDlQu5Fxw
T3+uOPzFItmN4Z5ZHCrtQbtu0cZ5GM9B1pl0Z1gcuI3HRSoIbJ4GOvOf8ilW5ufswd7NxIFBZN4P
PcDGc98etGttAJRbqB88krHuxcj+WBVW4x5DNFHMwHKyGQ7Rz15PTvnHT1qaE/bI/MlUhCx2xn0B
xk+v+frRdzL5bwIWaZkO1I2w3Tr1GKFe4BI88sZjWDazDBYv8uO+CMnPpkCniF2UK5EcYGBHESMf
iMfpimQSqkEUccZfEathBgAHp94j3/KpBJO2SIFUZ6O+D+gNAEMTLBdTRHcBhWRQS2c5yQOuc9QP
Y9+LiwtLzJuRf7oOCfqRUVikpubieXYMgRhV7YyeT/wKr1enh8LGynLVmbl0EVFRQqKFUdABgClo
oruJCiiigAooooAKKKKACiiigAooooAKxZ7lhqDbSY7eRgu9QCWZRyee3QZwfu++a2qqS2SiY3Fu
qJMRhsjhx6E9vr/OsMRTlOFojTsyrKq+V5iStMwPyKXypftnH547VXZ9S4gYIxySXRvmdd3pwF4I
7k9cc81dRYJJvMMKrcJjduUb149fz5pDKPtUhbhIY8luvXk/kFH514+qdmjQas7QsscsQjQgCPYx
Yk+mMenPfv6U62KSNLNGwKO2Bj24P45B/KkF4pVX8mYRn+MpgDjPI6/pUMUFw2XS4McbSOdgUHgk
8gnPPf056VNvkMdcESM0wldI7dWJOzcC30xzjB6etWoXMkMchUoWUEqRgjI6VAbMskkRnkETAhQp
5APXk9etMSc3W2GN8lWPmtnlQGxjjucY/P2otdaAOVX88xRTFYlGWBAJU9gPb6g+1WIoliUgEkkk
lj1J9TVaaK2iZV8pmeXgKrEbiATnr19+tPW3M0OLh5CWGGQkY9xx1FDAY6xw6hCVfY0itlc8MBjt
65P6n1q4CCMg5BqrNAkVpL5UAciM7I+3TgD07dKLXTQbSNGuS0By3logVGUnIXBGcY4xW1KhKt8P
QTdia2cS3W+MPsMfLFSAeRtwSOerdP8ACrtHSivYp01TioozbuFFFFWIKKKKACiiigAooooAKKKK
ACiiigAooooAimgSbaTlXX7rqcEf59KoSRXFusitukEr8yoPujGOnODge4zzx0rUorGrQhU3Gm0U
lWKWAKpDR4wNp/qKciLGiogwqgAD0FTPbQyOXKYc9WU4J/EU37HEBwZQex8xj/M1wywE+jK5yKZz
HC7jqqk9KSCPyoQuME5ZuO5OT+pNSmyhYEN5hyMHMrc/hmkNqynMU7D/AGXG4f4/rUvA1EtGh8yK
1zdW0Y2SlHYsF8vIznt16U5HMMESSFnlK4A6sxxUM5ntpnla2Yx7CzeWd4ZgBjjqOB1wB0q9bQLG
vmH55XGWkIwT7ew9v60UsJKTtLRA5EcSG5ZzIssaqdoUkqSe5yOo7ccdatIixoFRQqjoAKdRXpU6
UaatEhu4UUUVoIKKKKACiiigAooooAKKKKACiiigAooooAKKKKACiiigAooooAKKKKACiiigAooo
oAKKKKACiiigAooooAKKKKACiiigD//Z</Data></Thumbnail></Binary><mdContact><rpIndName>Population Division</rpIndName><rpOrgName>U.S. Census Bureau</rpOrgName><rpCntInfo><cntPhone><voiceNum tddtty="">301-763-2419</voiceNum></cntPhone><cntAddress addressType="postal"><delPoint>4600 Silver Hill Rd</delPoint><city>Washington</city><adminArea>DC</adminArea><postCode>20233-8800</postCode><eMailAdd>pop.global.map.list@census.gov</eMailAdd><country>US</country></cntAddress></rpCntInfo><role><RoleCd value="011">11</RoleCd></role><displayName>U.S. Census Bureau</displayName></mdContact></metadata>
